{
  "x": 16,
  "y": 2,
  "w": 55,
  "h": 22,
  "title": "example 2",
  "name_id": "Form1",
  "controls": [
    {
      "x": 16,
      "y": 17,
      "w": 12,
      "h": 3,
      "tool_type": 3,
      "name_id": "btnOK",
      "caption": "OK",
      "code": "def on_click_btnOK():\n    msgbox(\"OK button clicked!\")\n    txtOutput.caption=\"Welcome \"+txtName.caption+\"!\"\n",
      "value": false,
      "items": [],
      "list_index": 0,
      "scroll_offset": 0
    },
    {
      "x": 9,
      "y": 20,
      "w": 31,
      "h": 1,
      "tool_type": 13,
      "name_id": "txtOutput",
      "caption": "Please click ok!",
      "code": "",
      "value": false,
      "items": [],
      "list_index": 0,
      "scroll_offset": 0
    },
    {
      "x": 8,
      "y": 16,
      "w": 31,
      "h": 1,
      "tool_type": 13,
      "name_id": "txtName",
      "caption": "Enter your name here!",
      "code": "",
      "value": false,
      "items": [],
      "list_index": 0,
      "scroll_offset": 0
    },
    {
      "x": 8,
      "y": 10,
      "w": 20,
      "h": 6,
      "tool_type": 7,
      "name_id": "ctrl4",
      "caption": "gender",
      "code": "",
      "value": false,
      "items": [],
      "list_index": 0,
      "scroll_offset": 0
    },
    {
      "x": 10,
      "y": 11,
      "w": 16,
      "h": 1,
      "tool_type": 11,
      "name_id": "opt1",
      "caption": "Male",
      "code": "",
      "value": false,
      "items": [],
      "list_index": 0,
      "scroll_offset": 0
    },
    {
      "x": 10,
      "y": 12,
      "w": 16,
      "h": 1,
      "tool_type": 11,
      "name_id": "opt2",
      "caption": "Female",
      "code": "",
      "value": false,
      "items": [],
      "list_index": 0,
      "scroll_offset": 0
    },
    {
      "x": 10,
      "y": 13,
      "w": 16,
      "h": 1,
      "tool_type": 11,
      "name_id": "opt3",
      "caption": "non-binary",
      "code": "",
      "value": false,
      "items": [],
      "list_index": 0,
      "scroll_offset": 0
    },
    {
      "x": 10,
      "y": 14,
      "w": 16,
      "h": 1,
      "tool_type": 1,
      "name_id": "chk1",
      "caption": "Trans",
      "code": "",
      "value": false,
      "items": [],
      "list_index": 0,
      "scroll_offset": 0
    },
    {
      "x": 8,
      "y": 1,
      "w": 20,
      "h": 9,
      "tool_type": 7,
      "name_id": "ctrl9",
      "caption": "Generation",
      "code": "",
      "value": false,
      "items": [],
      "list_index": 0,
      "scroll_offset": 0
    },
    {
      "x": 11,
      "y": 2,
      "w": 15,
      "h": 1,
      "tool_type": 11,
      "name_id": "optGreat",
      "caption": "Great Gen. ",
      "code": "",
      "value": false,
      "items": [],
      "list_index": 0,
      "scroll_offset": 0
    },
    {
      "x": 11,
      "y": 3,
      "w": 15,
      "h": 1,
      "tool_type": 11,
      "name_id": "optScilent",
      "caption": "Silent Gen. ",
      "code": "",
      "value": false,
      "items": [],
      "list_index": 0,
      "scroll_offset": 0
    },
    {
      "x": 11,
      "y": 4,
      "w": 15,
      "h": 1,
      "tool_type": 11,
      "name_id": "optBoom",
      "caption": "Boomer Gen. ",
      "code": "",
      "value": false,
      "items": [],
      "list_index": 0,
      "scroll_offset": 0
    },
    {
      "x": 11,
      "y": 5,
      "w": 15,
      "h": 1,
      "tool_type": 11,
      "name_id": "optX",
      "caption": "Gen X",
      "code": "",
      "value": false,
      "items": [],
      "list_index": 0,
      "scroll_offset": 0
    },
    {
      "x": 11,
      "y": 6,
      "w": 15,
      "h": 1,
      "tool_type": 11,
      "name_id": "optY",
      "caption": "Gen Y",
      "code": "",
      "value": false,
      "items": [],
      "list_index": 0,
      "scroll_offset": 0
    },
    {
      "x": 11,
      "y": 7,
      "w": 15,
      "h": 1,
      "tool_type": 11,
      "name_id": "optZ",
      "caption": "Gen Z",
      "code": "",
      "value": false,
      "items": [],
      "list_index": 0,
      "scroll_offset": 0
    },
    {
      "x": 11,
      "y": 8,
      "w": 15,
      "h": 1,
      "tool_type": 11,
      "name_id": "optAlph",
      "caption": "Gen. Alpha",
      "code": "",
      "value": false,
      "items": [],
      "list_index": 0,
      "scroll_offset": 0
    }
  ]
}